docs/converted_cypher.txt
docs/customer_product_bought.csv
docs/gremlin_samples.py
docs/notes.txt
docs/todos.txt
docs/configs/csv/multiple_edges_multiple_nodes.json
docs/configs/csv/multiple_edges_single_node.json
docs/configs/csv/single_edge_multiple_nodes.json
docs/configs/csv/single_edge_single_node.json
docs/configs/pgsql/multiple_edges_multiple_nodes.json
docs/configs/pgsql/multiple_edges_single_node.json
docs/configs/pgsql/single_edge_multiple_nodes.json
docs/configs/pgsql/single_edge_single_node.json
agefreighter/__init__.py
agefreighter/agefreighter.py
agefreighter/converter.py
agefreighter/cosmosgremlinloader.py
agefreighter/cosmosnosqlexporter.py
agefreighter/csvdatamanager.py
agefreighter/csvexporter.py
agefreighter/cypherparser.py
agefreighter/generator.py
agefreighter/main.py
agefreighter/neo4jexporter.py
agefreighter/neo4jloader.py
agefreighter/parser.out
agefreighter/pgsqlexporter.py
agefreighter/pgsqlloader.py
agefreighter/view.py
agefreighter/templates/converter_cache
agefreighter/templates/index.html
agefreighter-1.0.28.dist-info/METADATA
agefreighter-1.0.28.dist-info/WHEEL
agefreighter-1.0.28.dist-info/entry_points.txt
agefreighter-1.0.28.dist-info/licenses/LICENSE
agefreighter-1.0.28.dist-info/RECORD
