Metadata-Version: 2.4
Name: agefreighter
Version: 1.0.28
Summary: a Python package that helps you to create a graph database using Azure Database for PostgreSQL.
Project-URL: Homepage, https://github.com/rioriost/agefreighter
Project-URL: Issues, https://github.com/rioriost/agefreighter/issues
Author-email: Rio Fujita <rifujita@microsoft.com>
License: MIT License
License-File: LICENSE
Requires-Python: >=3.13
Requires-Dist: aiofiles>=25.1.0
Requires-Dist: argcomplete>=3.6.3
Requires-Dist: numpy>=2.4.1
Requires-Dist: psycopg-binary>=3.3.2
Requires-Dist: psycopg-pool>=3.3.0
Requires-Dist: shtab>=1.8.0
